{"bugs":[{"creation_time":"2020-01-02T13:46:45Z","component":"Theme","resolution":"INCOMPLETE","priority":"P3","op_sys":"macOS","status":"RESOLVED","last_change_time":"2024-06-28T09:36:11Z","severity":"S3","id":1606631,"summary":"Inefficient z-ordering of elements in the browser UI, causes large layers with current WebRender heuristics","keywords":["perf:resource-use"]},{"status":"RESOLVED","keywords":["perf","perf:responsiveness"],"component":"Graphics: WebRender","creation_time":"2021-05-06T04:02:44Z","resolution":"INACTIVE","last_change_time":"2024-05-06T19:32:16Z","op_sys":"Unspecified","severity":"S3","summary":"Menus show a delay of 4-5 seconds on mouse input (Wayland/WebRnender?)","id":1709763,"priority":"--"},{"resolution":"WORKSFORME","creation_time":"2022-04-24T19:22:21Z","component":"Performance","keywords":["perf:responsiveness"],"status":"RESOLVED","priority":"--","summary":"Firefox becomes really slow to respond/switch to on MacBook Pro M1 Max","id":1766181,"last_change_time":"2024-11-09T13:51:42Z","op_sys":"Unspecified","severity":"--"},{"component":"PDF Viewer","creation_time":"2022-08-19T06:50:58Z","resolution":"WORKSFORME","status":"RESOLVED","keywords":["regression"],"priority":"P3","op_sys":"Unspecified","severity":"S3","last_change_time":"2024-05-02T16:48:19Z","summary":"Slow rendering and opening of certain PDF types","id":1785979},{"resolution":"INCOMPLETE","priority":"--","component":"Performance","creation_time":"2023-04-26T10:47:40Z","keywords":[],"id":1830037,"summary":"GC overhead resulting 100% CPU usage and ending up freezes/hangs after each 30-60sec and occasionally panics on macOS","status":"RESOLVED","op_sys":"Unspecified","last_change_time":"2023-12-04T12:24:31Z","severity":"S3"},{"id":1844961,"summary":"linkedin.com will crash the whole computer (El Capitain, Mac OS X 10.11.6) by using up the whole storage. The browser task (FirefoxCP Web Content) grows and grows in the GByte ranges.","keywords":[],"status":"RESOLVED","last_change_time":"2024-05-06T19:53:32Z","severity":"--","op_sys":"macOS","priority":"--","resolution":"INACTIVE","creation_time":"2023-07-22T23:26:31Z","component":"Performance"},{"status":"RESOLVED","op_sys":"Unspecified","last_change_time":"2024-03-01T21:22:53Z","severity":"--","keywords":[],"id":1866066,"summary":"Firefox freezes completely at irregular intervals","component":"Disability Access APIs","creation_time":"2023-11-22T14:21:41Z","priority":"--","resolution":"DUPLICATE"},{"priority":"--","resolution":"INCOMPLETE","creation_time":"2023-12-17T20:51:14Z","component":"Performance","id":1870532,"summary":"Firefox 120.0.1 grabs 100% of cpu resources and freezes","keywords":[],"last_change_time":"2025-02-03T04:39:58Z","status":"RESOLVED","op_sys":"Unspecified","severity":"--"},{"severity":"--","last_change_time":"2024-02-09T16:02:16Z","op_sys":"Unspecified","status":"RESOLVED","keywords":[],"summary":"Permanent increase of page memory usage under Ubuntu 22.04","id":1871856,"component":"Performance","creation_time":"2023-12-25T13:00:34Z","priority":"--","resolution":"INVALID"},{"priority":"--","resolution":"INCOMPLETE","creation_time":"2023-12-29T15:47:58Z","component":"Performance","summary":"Since the last update 121.0 Firefox uses insane amount of Ram 99% of my 32GB without any real reason and if it gets closed it buges out for 10 seconds spikes over the ram limit just to slowly close","id":1872368,"keywords":[],"op_sys":"Unspecified","severity":"--","last_change_time":"2024-07-01T12:23:26Z","status":"RESOLVED"},{"status":"RESOLVED","op_sys":"Unspecified","last_change_time":"2024-07-01T12:25:21Z","severity":"--","summary":"Firefox lags after latest update, high memory use (121.0 12-2023)","id":1872414,"keywords":[],"creation_time":"2023-12-30T00:34:35Z","component":"Performance","priority":"--","resolution":"INCOMPLETE"},{"op_sys":"Unspecified","severity":"--","last_change_time":"2024-08-05T12:18:30Z","summary":"firefox using 3.4gb of memory with a few tabs open","id":1876708,"priority":"--","status":"RESOLVED","keywords":["perf:resource-use","perf:responsiveness"],"creation_time":"2024-01-26T11:03:08Z","component":"Performance","resolution":"INCOMPLETE"},{"id":1877007,"summary":"extremely high CPU usage even with one tab open on the splash screen","keywords":["perf:resource-use"],"status":"RESOLVED","last_change_time":"2024-08-05T12:18:25Z","severity":"--","op_sys":"Unspecified","resolution":"INCOMPLETE","priority":"--","creation_time":"2024-01-28T16:15:06Z","component":"Performance"},{"keywords":["perf:resource-use"],"id":1879177,"summary":"3 youtube tabs are using 7GB of RAM","status":"RESOLVED","severity":"--","last_change_time":"2024-08-05T15:01:21Z","op_sys":"Unspecified","priority":"--","resolution":"INVALID","component":"Performance","creation_time":"2024-02-07T20:00:44Z"},{"resolution":"INCOMPLETE","priority":"--","creation_time":"2024-02-12T02:38:12Z","component":"Performance","id":1879788,"summary":"Firefox Freezes But Websites Don't","keywords":[],"status":"RESOLVED","op_sys":"Unspecified","severity":"--","last_change_time":"2024-03-13T14:26:26Z"},{"component":"Performance","creation_time":"2024-02-12T17:13:40Z","priority":"--","resolution":"INCOMPLETE","last_change_time":"2024-09-02T12:20:43Z","op_sys":"Unspecified","severity":"--","status":"RESOLVED","keywords":["perf:resource-use"],"id":1879905,"summary":"firefox consuming 2 GB of RAM with 8 tabs open"},{"priority":"--","resolution":"","creation_time":"2024-02-14T13:36:20Z","component":"Performance","id":1880287,"summary":"tiktok.com - Live videos stop working after a few minutes, stuck loading","keywords":[],"status":"NEW","op_sys":"Windows 10","last_change_time":"2024-11-09T13:56:39Z","severity":"S3"},{"creation_time":"2024-02-29T23:13:16Z","component":"Performance","resolution":"","status":"UNCONFIRMED","keywords":[],"priority":"--","op_sys":"Unspecified","last_change_time":"2024-05-21T13:37:47Z","severity":"--","id":1882916,"summary":"Firefox consumes a lot of CPU and makes me Mac M2 hang for a good 15 seconds"},{"component":"Tabbed Browser","creation_time":"2024-03-01T03:39:28Z","resolution":"INCOMPLETE","priority":"--","status":"RESOLVED","severity":"--","last_change_time":"2024-09-02T12:21:23Z","op_sys":"Unspecified","keywords":[],"id":1882952,"summary":"Firefox Browser Freezes when Opening Multiple Tabs"},{"keywords":[],"status":"RESOLVED","resolution":"INCOMPLETE","component":"Performance","creation_time":"2024-03-03T06:48:48Z","summary":"firefox using large amount of memory","id":1883246,"op_sys":"Unspecified","last_change_time":"2024-09-02T12:20:29Z","severity":"--","priority":"--"},{"component":"Performance","creation_time":"2024-03-04T19:20:05Z","priority":"--","resolution":"","status":"UNCONFIRMED","severity":"--","last_change_time":"2024-10-08T17:34:50Z","op_sys":"Unspecified","keywords":[],"summary":"huge amount of memory storage (constantly) idk why pls help/.................................................................................................................................................","id":1883475},{"id":1883507,"summary":"Memory usage is too high 23GB and up to 60% CPU usage.","keywords":[],"last_change_time":"2024-10-08T17:35:15Z","status":"UNCONFIRMED","severity":"--","op_sys":"Unspecified","resolution":"","priority":"--","creation_time":"2024-03-04T22:03:15Z","component":"Performance"},{"op_sys":"Unspecified","severity":"--","last_change_time":"2024-10-08T17:34:40Z","id":1883669,"summary":"Memory Problem","priority":"--","status":"UNCONFIRMED","keywords":[],"creation_time":"2024-03-05T15:09:26Z","component":"Performance","resolution":""},{"component":"Performance","creation_time":"2024-03-08T03:56:55Z","resolution":"","priority":"--","op_sys":"Unspecified","last_change_time":"2024-10-08T17:34:42Z","status":"UNCONFIRMED","severity":"S3","keywords":["memory-footprint"],"summary":"Firefox is using lots of memory when only having several tabs open","id":1884296},{"creation_time":"2024-03-17T18:24:37Z","component":"Performance","priority":"--","resolution":"","op_sys":"Unspecified","last_change_time":"2024-10-08T17:34:54Z","severity":"--","status":"UNCONFIRMED","summary":"Use to many Ram","id":1885796,"keywords":[]},{"creation_time":"2024-04-14T09:00:25Z","component":"Performance","priority":"--","resolution":"","last_change_time":"2024-10-08T17:35:31Z","severity":"--","op_sys":"Unspecified","status":"UNCONFIRMED","summary":"Enourmous RAM usage (60Gig)","id":1891345,"keywords":[]},{"keywords":[],"summary":"Update xsimd to new version 7eb009bca73e5cc51d05dcfcda25dfb74d6e0aaa from 2024-03-28 13:40:05","id":1891462,"status":"RESOLVED","last_change_time":"2024-04-26T08:53:42Z","severity":"--","op_sys":"Unspecified","priority":"--","resolution":"FIXED","component":"Performance","creation_time":"2024-04-15T12:23:03Z"},{"keywords":[],"id":1893080,"summary":"Uses a lot of ram, literally a lot even for less number of tabs opened","last_change_time":"2025-01-06T12:15:23Z","status":"RESOLVED","severity":"--","op_sys":"Unspecified","resolution":"INCOMPLETE","priority":"--","component":"Performance","creation_time":"2024-04-23T23:06:49Z"},{"summary":"Memory Leak (Isolated Web Container)","id":1893459,"keywords":[],"severity":"--","status":"RESOLVED","last_change_time":"2024-12-02T12:31:51Z","op_sys":"Unspecified","resolution":"INCOMPLETE","priority":"--","creation_time":"2024-04-25T13:36:23Z","component":"Performance"},{"resolution":"INACTIVE","priority":"--","creation_time":"2024-05-22T16:49:19Z","component":"Performance","summary":"firefox slows down, needs relaunch to restore throughput","id":1898319,"keywords":[],"status":"RESOLVED","severity":"--","last_change_time":"2025-01-06T17:00:36Z","op_sys":"Linux"},{"last_change_time":"2024-09-09T14:01:12Z","severity":"--","op_sys":"Windows 11","id":1908857,"summary":"www3.nhk.or.jp - The website is loaded after 1-2 seconds of blank page","priority":"P3","status":"NEW","keywords":[],"creation_time":"2024-07-19T09:07:38Z","component":"Performance","resolution":""},{"component":"Performance","creation_time":"2024-08-12T13:10:00Z","priority":"--","resolution":"","last_change_time":"2024-11-09T15:02:19Z","severity":"--","status":"UNCONFIRMED","op_sys":"Unspecified","keywords":[],"id":1912758,"summary":"Extreme CPU usage spike when typing into text fields"},{"component":"Performance","creation_time":"2024-08-16T04:45:39Z","resolution":"","priority":"--","status":"UNCONFIRMED","last_change_time":"2024-11-09T15:22:28Z","op_sys":"Unspecified","severity":"--","keywords":[],"id":1913407,"summary":"the browser go crazy with cpu usage recently https://share.firefox.dev/3yIbAKI"},{"component":"Performance","creation_time":"2024-08-24T16:10:13Z","resolution":"","priority":"--","status":"UNCONFIRMED","op_sys":"Unspecified","severity":"--","last_change_time":"2025-01-16T20:28:26Z","keywords":[],"id":1914733,"summary":"YouTube Freezing and consuming CPU usage"},{"keywords":[],"status":"UNCONFIRMED","resolution":"","creation_time":"2024-09-11T10:37:14Z","component":"Performance","id":1918065,"summary":"High CPU/RAM utilisation using Firefox ESR without internet connectivity","severity":"--","op_sys":"Unspecified","last_change_time":"2024-12-02T11:07:56Z","priority":"--"},{"op_sys":"Windows 11","severity":"--","last_change_time":"2024-12-31T10:59:46Z","id":1923941,"summary":"Firefox stops responding, 23 seconds in gfxDWriteFontList::ReadFaceNamesForFamily","priority":"--","status":"UNCONFIRMED","keywords":[],"component":"Performance","creation_time":"2024-10-10T18:25:27Z","resolution":""},{"id":1924642,"summary":"Parent process and content processes sometimes consume lots of CPU (Tons of IPCOut — PContent::Msg_ScriptError)","keywords":[],"last_change_time":"2024-12-26T14:10:54Z","op_sys":"Unspecified","severity":"--","status":"UNCONFIRMED","resolution":"","priority":"--","creation_time":"2024-10-15T08:05:21Z","component":"Performance"},{"creation_time":"2024-10-30T14:33:29Z","component":"Performance","resolution":"WORKSFORME","priority":"--","op_sys":"Unspecified","status":"RESOLVED","severity":"--","last_change_time":"2024-12-26T14:34:32Z","summary":"Wiki page caused high CPU and RAM usage permanently","id":1928090,"keywords":[]},{"keywords":["perf"],"summary":"since update 115.17.0esr (64 bits) my computer freezes and firefox takes 100% of the memory","id":1929575,"status":"UNCONFIRMED","severity":"--","last_change_time":"2024-12-26T14:21:04Z","op_sys":"Unspecified","priority":"--","resolution":"","component":"Performance","creation_time":"2024-11-06T14:38:42Z"},{"component":"Performance","creation_time":"2024-11-13T20:08:36Z","resolution":"INACTIVE","priority":"--","last_change_time":"2025-01-13T15:26:58Z","status":"RESOLVED","severity":"--","op_sys":"Unspecified","keywords":[],"id":1931051,"summary":"Firefox freezes on arch linux"},{"keywords":[],"summary":"Slow poor scrolling performance when using dual monitors.","id":1931371,"status":"UNCONFIRMED","op_sys":"Windows 10","severity":"--","last_change_time":"2024-12-26T14:36:27Z","resolution":"","priority":"--","component":"Performance","creation_time":"2024-11-14T16:01:57Z"},{"component":"Performance","creation_time":"2024-11-21T12:52:00Z","priority":"--","resolution":"","status":"NEW","op_sys":"Windows 10","last_change_time":"2025-01-30T07:59:42Z","severity":"--","keywords":["webcompat:site-report"],"id":1932607,"summary":"nypost.com - Opening articles in multiple tabs crashes the browser (not responding)"},{"resolution":"","creation_time":"2024-12-10T01:02:56Z","component":"Performance","keywords":[],"status":"UNCONFIRMED","priority":"--","summary":"Memory leak in mac M1","id":1936166,"last_change_time":"2025-01-27T15:31:15Z","op_sys":"Unspecified","severity":"--"},{"id":1939360,"summary":"Deleting files from Google Drive with a huge amount of files within a folder is very slow and causes high CPU load","keywords":["perf","power"],"status":"NEW","op_sys":"Unspecified","last_change_time":"2025-01-06T13:36:46Z","severity":"--","priority":"--","resolution":"","creation_time":"2024-12-28T21:20:57Z","component":"Performance"},{"creation_time":"2024-12-30T13:04:04Z","component":"Performance","priority":"--","resolution":"","last_change_time":"2025-02-03T17:19:52Z","status":"UNCONFIRMED","op_sys":"Unspecified","severity":"--","id":1939474,"summary":"slowness","keywords":[]}]}