{"bugs":[{"status":"RESOLVED","severity":"S3","op_sys":"Unspecified","keywords":["perf","perf:responsiveness"],"resolution":"INACTIVE","summary":"Menus show a delay of 4-5 seconds on mouse input (Wayland/WebRnender?)","creation_time":"2021-05-06T04:02:44Z","priority":"--","id":1709763,"component":"Graphics: WebRender","last_change_time":"2024-05-06T19:32:16Z"},{"creation_time":"2022-04-24T19:22:21Z","op_sys":"Unspecified","severity":"--","status":"RESOLVED","summary":"Firefox becomes really slow to respond/switch to on MacBook Pro M1 Max","resolution":"WORKSFORME","keywords":["perf:responsiveness"],"id":1766181,"priority":"--","component":"Performance: Responsiveness","last_change_time":"2025-03-21T01:04:05Z"},{"status":"RESOLVED","severity":"S3","op_sys":"Unspecified","resolution":"INCOMPLETE","keywords":[],"summary":"GC overhead resulting 100% CPU usage and ending up freezes/hangs after each 30-60sec and occasionally panics on macOS","priority":"--","id":1830037,"creation_time":"2023-04-26T10:47:40Z","last_change_time":"2023-12-04T12:24:31Z","component":"Performance: General"},{"creation_time":"2023-07-22T23:26:31Z","summary":"linkedin.com will crash the whole computer (El Capitain, Mac OS X 10.11.6) by using up the whole storage. The browser task (FirefoxCP Web Content) grows and grows in the GByte ranges.","keywords":[],"resolution":"INACTIVE","op_sys":"macOS","severity":"--","status":"RESOLVED","component":"Performance: General","last_change_time":"2024-05-06T19:53:32Z","id":1844961,"priority":"--"},{"op_sys":"Unspecified","severity":"--","status":"RESOLVED","summary":"Firefox freezes completely at irregular intervals","resolution":"DUPLICATE","keywords":[],"id":1866066,"priority":"--","component":"Disability Access APIs","last_change_time":"2024-03-01T21:22:53Z","creation_time":"2023-11-22T14:21:41Z"},{"op_sys":"Unspecified","severity":"--","status":"RESOLVED","summary":"Firefox 120.0.1 grabs 100% of cpu resources and freezes","resolution":"INCOMPLETE","keywords":[],"creation_time":"2023-12-17T20:51:14Z","id":1870532,"priority":"--","last_change_time":"2025-02-03T04:39:58Z","component":"Performance: General"},{"priority":"--","id":1871856,"last_change_time":"2024-02-09T16:02:16Z","component":"Performance: General","creation_time":"2023-12-25T13:00:34Z","severity":"--","status":"RESOLVED","op_sys":"Unspecified","resolution":"INVALID","keywords":[],"summary":"Permanent increase of page memory usage under Ubuntu 22.04"},{"id":1872368,"priority":"--","last_change_time":"2024-07-01T12:23:26Z","component":"Performance: General","creation_time":"2023-12-29T15:47:58Z","op_sys":"Unspecified","status":"RESOLVED","severity":"--","summary":"Since the last update 121.0 Firefox uses insane amount of Ram 99% of my 32GB without any real reason and if it gets closed it buges out for 10 seconds spikes over the ram limit just to slowly close","resolution":"INCOMPLETE","keywords":[]},{"keywords":[],"resolution":"INCOMPLETE","summary":"Firefox lags after latest update, high memory use (121.0 12-2023)","severity":"--","status":"RESOLVED","op_sys":"Unspecified","component":"Performance: General","last_change_time":"2024-07-01T12:25:21Z","creation_time":"2023-12-30T00:34:35Z","priority":"--","id":1872414},{"priority":"--","id":1876708,"component":"Performance: Responsiveness","last_change_time":"2025-03-21T01:04:43Z","status":"RESOLVED","severity":"--","op_sys":"Unspecified","resolution":"INCOMPLETE","keywords":["perf:resource-use","perf:responsiveness"],"summary":"firefox using 3.4gb of memory with a few tabs open","creation_time":"2024-01-26T11:03:08Z"},{"id":1877007,"priority":"--","creation_time":"2024-01-28T16:15:06Z","last_change_time":"2024-08-05T12:18:25Z","component":"Performance: General","op_sys":"Unspecified","status":"RESOLVED","severity":"--","summary":"extremely high CPU usage even with one tab open on the splash screen","resolution":"INCOMPLETE","keywords":["perf:resource-use"]},{"summary":"3 youtube tabs are using 7GB of RAM","resolution":"INVALID","keywords":["perf:resource-use"],"op_sys":"Unspecified","severity":"--","status":"RESOLVED","last_change_time":"2024-08-05T15:01:21Z","component":"Performance: General","creation_time":"2024-02-07T20:00:44Z","id":1879177,"priority":"--"},{"id":1879788,"priority":"--","component":"Performance: General","last_change_time":"2024-03-13T14:26:26Z","op_sys":"Unspecified","severity":"--","status":"RESOLVED","summary":"Firefox Freezes But Websites Don't","resolution":"INCOMPLETE","keywords":[],"creation_time":"2024-02-12T02:38:12Z"},{"component":"Performance: General","last_change_time":"2024-09-02T12:20:43Z","id":1879905,"priority":"--","summary":"firefox consuming 2 GB of RAM with 8 tabs open","keywords":["perf:resource-use"],"resolution":"INCOMPLETE","op_sys":"Unspecified","status":"RESOLVED","severity":"--","creation_time":"2024-02-12T17:13:40Z"},{"status":"NEW","severity":"S3","op_sys":"Windows 10","keywords":[],"resolution":"","summary":"tiktok.com - Live videos stop working after a few minutes, stuck loading","priority":"--","id":1880287,"creation_time":"2024-02-14T13:36:20Z","component":"Performance: General","last_change_time":"2025-04-21T12:27:03Z"},{"priority":"--","id":1882916,"last_change_time":"2024-05-21T13:37:47Z","component":"Performance: General","severity":"--","status":"UNCONFIRMED","op_sys":"Unspecified","keywords":[],"resolution":"","summary":"Firefox consumes a lot of CPU and makes me Mac M2 hang for a good 15 seconds","creation_time":"2024-02-29T23:13:16Z"},{"op_sys":"Unspecified","severity":"--","status":"RESOLVED","summary":"firefox using large amount of memory","keywords":[],"resolution":"INCOMPLETE","id":1883246,"priority":"--","last_change_time":"2024-09-02T12:20:29Z","component":"Performance: General","creation_time":"2024-03-03T06:48:48Z"},{"component":"Performance: General","last_change_time":"2024-10-08T17:34:50Z","priority":"--","id":1883475,"creation_time":"2024-03-04T19:20:05Z","resolution":"","keywords":[],"summary":"huge amount of memory storage (constantly) idk why pls help/.................................................................................................................................................","status":"UNCONFIRMED","severity":"--","op_sys":"Unspecified"},{"last_change_time":"2024-10-08T17:35:15Z","component":"Performance: General","creation_time":"2024-03-04T22:03:15Z","priority":"--","id":1883507,"keywords":[],"resolution":"","summary":"Memory usage is too high 23GB and up to 60% CPU usage.","severity":"--","status":"UNCONFIRMED","op_sys":"Unspecified"},{"last_change_time":"2024-10-08T17:34:40Z","component":"Performance: General","priority":"--","id":1883669,"resolution":"","keywords":[],"summary":"Memory Problem","status":"UNCONFIRMED","severity":"--","op_sys":"Unspecified","creation_time":"2024-03-05T15:09:26Z"},{"creation_time":"2024-03-08T03:56:55Z","last_change_time":"2024-10-08T17:34:42Z","component":"Performance: General","priority":"--","id":1884296,"resolution":"","keywords":["memory-footprint"],"summary":"Firefox is using lots of memory when only having several tabs open","status":"UNCONFIRMED","severity":"S3","op_sys":"Unspecified"},{"resolution":"INCOMPLETE","keywords":[],"summary":"Use to many Ram","status":"RESOLVED","severity":"--","op_sys":"Unspecified","creation_time":"2024-03-17T18:24:37Z","last_change_time":"2025-03-31T12:27:19Z","component":"Performance: General","priority":"--","id":1885796},{"creation_time":"2024-04-14T09:00:25Z","resolution":"","keywords":[],"summary":"Enourmous RAM usage (60Gig)","severity":"--","status":"UNCONFIRMED","op_sys":"Unspecified","last_change_time":"2024-10-08T17:35:31Z","component":"Performance: General","priority":"--","id":1891345},{"last_change_time":"2024-04-26T08:53:42Z","component":"Performance: General","creation_time":"2024-04-15T12:23:03Z","id":1891462,"priority":"--","summary":"Update xsimd to new version 7eb009bca73e5cc51d05dcfcda25dfb74d6e0aaa from 2024-03-28 13:40:05","keywords":[],"resolution":"FIXED","op_sys":"Unspecified","severity":"--","status":"RESOLVED"},{"last_change_time":"2025-01-06T12:15:23Z","component":"Performance: General","creation_time":"2024-04-23T23:06:49Z","priority":"--","id":1893080,"resolution":"INCOMPLETE","keywords":[],"summary":"Uses a lot of ram, literally a lot even for less number of tabs opened","severity":"--","status":"RESOLVED","op_sys":"Unspecified"},{"creation_time":"2024-04-25T13:36:23Z","keywords":[],"resolution":"INCOMPLETE","summary":"Memory Leak (Isolated Web Container)","status":"RESOLVED","severity":"--","op_sys":"Unspecified","last_change_time":"2024-12-02T12:31:51Z","component":"Performance: General","priority":"--","id":1893459},{"component":"Performance: General","last_change_time":"2025-01-06T17:00:36Z","priority":"--","id":1898319,"creation_time":"2024-05-22T16:49:19Z","resolution":"INACTIVE","keywords":[],"summary":"firefox slows down, needs relaunch to restore throughput","status":"RESOLVED","severity":"--","op_sys":"Linux"},{"component":"Performance: General","last_change_time":"2025-03-31T09:59:19Z","priority":"P3","id":1908857,"resolution":"FIXED","keywords":[],"summary":"www3.nhk.or.jp - The website is loaded after 1-2 seconds of blank page","status":"RESOLVED","severity":"--","op_sys":"Windows 11","creation_time":"2024-07-19T09:07:38Z"},{"resolution":"INCOMPLETE","keywords":[],"summary":"Extreme CPU usage spike when typing into text fields","severity":"--","status":"RESOLVED","op_sys":"Unspecified","component":"Performance: General","last_change_time":"2025-05-05T12:25:43Z","creation_time":"2024-08-12T13:10:00Z","priority":"--","id":1912758},{"resolution":"INCOMPLETE","keywords":[],"summary":"the browser go crazy with cpu usage recently https://share.firefox.dev/3yIbAKI","severity":"--","status":"RESOLVED","op_sys":"Unspecified","last_change_time":"2025-05-05T12:26:59Z","component":"Performance: General","creation_time":"2024-08-16T04:45:39Z","priority":"--","id":1913407},{"summary":"YouTube Freezing and consuming CPU usage","keywords":[],"resolution":"INCOMPLETE","op_sys":"Unspecified","severity":"--","status":"RESOLVED","creation_time":"2024-08-24T16:10:13Z","last_change_time":"2025-04-07T12:30:44Z","component":"Performance: General","id":1914733,"priority":"--"},{"creation_time":"2024-09-11T10:37:14Z","component":"Performance: General","last_change_time":"2025-04-07T12:30:19Z","id":1918065,"priority":"--","summary":"High CPU/RAM utilisation using Firefox ESR without internet connectivity","keywords":[],"resolution":"INCOMPLETE","op_sys":"Unspecified","status":"RESOLVED","severity":"--"},{"summary":"Parent process and content processes sometimes consume lots of CPU (Tons of IPCOut — PContent::Msg_ScriptError)","keywords":[],"resolution":"WORKSFORME","op_sys":"Unspecified","severity":"--","status":"RESOLVED","component":"Performance: General","last_change_time":"2025-05-07T07:41:07Z","creation_time":"2024-10-15T08:05:21Z","id":1924642,"priority":"--"},{"severity":"--","status":"RESOLVED","op_sys":"Unspecified","keywords":[],"resolution":"WORKSFORME","summary":"Wiki page caused high CPU and RAM usage permanently","priority":"--","id":1928090,"last_change_time":"2024-12-26T14:34:32Z","component":"Performance: General","creation_time":"2024-10-30T14:33:29Z"},{"status":"UNCONFIRMED","severity":"--","op_sys":"Unspecified","resolution":"","keywords":["perf"],"summary":"since update 115.17.0esr (64 bits) my computer freezes and firefox takes 100% of the memory","priority":"--","id":1929575,"creation_time":"2024-11-06T14:38:42Z","last_change_time":"2024-12-26T14:21:04Z","component":"Performance: General"},{"id":1931051,"priority":"--","last_change_time":"2025-01-13T15:26:58Z","component":"Performance: General","creation_time":"2024-11-13T20:08:36Z","op_sys":"Unspecified","severity":"--","status":"RESOLVED","summary":"Firefox freezes on arch linux","resolution":"INACTIVE","keywords":[]},{"priority":"--","id":1931371,"creation_time":"2024-11-14T16:01:57Z","component":"Performance: General","last_change_time":"2024-12-26T14:36:27Z","status":"UNCONFIRMED","severity":"--","op_sys":"Windows 10","keywords":[],"resolution":"","summary":"Slow poor scrolling performance when using dual monitors."},{"summary":"nypost.com - Opening articles in multiple tabs crashes the browser (not responding)","resolution":"FIXED","keywords":["webcompat:site-report"],"op_sys":"Windows 10","status":"RESOLVED","severity":"--","creation_time":"2024-11-21T12:52:00Z","component":"Performance: General","last_change_time":"2025-04-23T12:49:42Z","id":1932607,"priority":"--"},{"creation_time":"2024-12-10T01:02:56Z","status":"UNCONFIRMED","severity":"--","op_sys":"Unspecified","resolution":"","keywords":[],"summary":"Memory leak in mac M1","priority":"--","id":1936166,"component":"Performance: General","last_change_time":"2025-01-27T15:31:15Z"},{"creation_time":"2024-12-24T16:19:48Z","last_change_time":"2025-05-07T08:54:47Z","component":"Performance: General","priority":"--","id":1939043,"resolution":"INCOMPLETE","keywords":[],"summary":"Gmail freezes on 2nd Gmail account","status":"RESOLVED","severity":"--","op_sys":"Unspecified"},{"op_sys":"Unspecified","severity":"--","status":"RESOLVED","summary":"slowness","keywords":[],"resolution":"INACTIVE","id":1939474,"priority":"--","last_change_time":"2025-02-24T15:22:43Z","component":"Performance: General","creation_time":"2024-12-30T13:04:04Z"},{"keywords":[],"resolution":"","summary":"paramountplus stream occasionally highly unresponsive","status":"NEW","severity":"--","op_sys":"Unspecified","creation_time":"2025-02-14T06:55:56Z","last_change_time":"2025-03-18T13:15:15Z","component":"Performance: General","priority":"--","id":1948186},{"component":"Performance: Responsiveness","last_change_time":"2025-04-25T13:16:59Z","creation_time":"2025-03-22T11:55:14Z","id":1955749,"priority":"P3","summary":"Severe jank when scrolling and clicking on messages in large message list on Yahoo Mail","keywords":[],"resolution":"","op_sys":"Unspecified","severity":"S3","status":"NEW"},{"op_sys":"Unspecified","severity":"S3","status":"UNCONFIRMED","summary":"High CPU usage after clicking buttons on at least one site","resolution":"","keywords":[],"id":1956931,"priority":"--","component":"Performance: Responsiveness","last_change_time":"2025-05-02T20:21:18Z","creation_time":"2025-03-27T20:24:11Z"},{"severity":"--","status":"UNCONFIRMED","op_sys":"Windows 11","resolution":"","keywords":[],"summary":"Dual monitor (laptop / Monitor) browsing very slow refresh in second monitor","creation_time":"2025-04-13T07:52:04Z","priority":"--","id":1960195,"last_change_time":"2025-05-09T12:11:00Z","component":"Graphics"},{"creation_time":"2020-01-02T13:46:45Z","last_change_time":"2024-06-28T09:36:11Z","component":"Theme","priority":"P3","id":1606631,"keywords":["perf:resource-use"],"resolution":"INCOMPLETE","summary":"Inefficient z-ordering of elements in the browser UI, causes large layers with current WebRender heuristics","status":"RESOLVED","severity":"S3","op_sys":"macOS"},{"keywords":["regression"],"resolution":"WORKSFORME","summary":"Slow rendering and opening of certain PDF types","severity":"S3","status":"RESOLVED","op_sys":"Unspecified","creation_time":"2022-08-19T06:50:58Z","component":"PDF Viewer","last_change_time":"2024-05-02T16:48:19Z","priority":"P3","id":1785979},{"op_sys":"Unspecified","severity":"--","status":"RESOLVED","summary":"Firefox Browser Freezes when Opening Multiple Tabs","keywords":[],"resolution":"INCOMPLETE","id":1882952,"priority":"--","component":"Tabbed Browser","last_change_time":"2024-09-02T12:21:23Z","creation_time":"2024-03-01T03:39:28Z"}]}