{"bugs":[{"resolution":"INACTIVE","keywords":["perf","perf:responsiveness"],"component":"Graphics: WebRender","priority":"--","id":1709763,"status":"RESOLVED","last_change_time":"2024-05-06T19:32:16Z","op_sys":"Unspecified","severity":"S3","summary":"Menus show a delay of 4-5 seconds on mouse input (Wayland/WebRnender?)","creation_time":"2021-05-06T04:02:44Z"},{"creation_time":"2022-04-24T19:22:21Z","summary":"Firefox becomes really slow to respond/switch to on MacBook Pro M1 Max","severity":"--","op_sys":"Unspecified","last_change_time":"2025-03-21T01:04:05Z","status":"RESOLVED","id":1766181,"priority":"--","component":"Performance: Responsiveness","keywords":["perf:responsiveness"],"resolution":"WORKSFORME"},{"creation_time":"2023-04-26T10:47:40Z","last_change_time":"2023-12-04T12:24:31Z","op_sys":"Unspecified","summary":"GC overhead resulting 100% CPU usage and ending up freezes/hangs after each 30-60sec and occasionally panics on macOS","status":"RESOLVED","keywords":[],"component":"Performance: General","resolution":"INCOMPLETE","severity":"S3","id":1830037,"priority":"--"},{"resolution":"INACTIVE","id":1844961,"keywords":[],"component":"Performance: General","priority":"--","status":"RESOLVED","creation_time":"2023-07-22T23:26:31Z","op_sys":"macOS","last_change_time":"2024-05-06T19:53:32Z","severity":"--","summary":"linkedin.com will crash the whole computer (El Capitain, Mac OS X 10.11.6) by using up the whole storage. The browser task (FirefoxCP Web Content) grows and grows in the GByte ranges."},{"id":1866066,"priority":"--","severity":"--","resolution":"DUPLICATE","component":"Disability Access APIs","keywords":[],"status":"RESOLVED","creation_time":"2023-11-22T14:21:41Z","summary":"Firefox freezes completely at irregular intervals","last_change_time":"2024-03-01T21:22:53Z","op_sys":"Unspecified"},{"severity":"--","id":1870532,"priority":"--","status":"RESOLVED","creation_time":"2023-12-17T20:51:14Z","op_sys":"Unspecified","last_change_time":"2025-02-03T04:39:58Z","summary":"Firefox 120.0.1 grabs 100% of cpu resources and freezes","resolution":"INCOMPLETE","keywords":[],"component":"Performance: General"},{"severity":"--","priority":"--","id":1871856,"last_change_time":"2024-02-09T16:02:16Z","op_sys":"Unspecified","summary":"Permanent increase of page memory usage under Ubuntu 22.04","creation_time":"2023-12-25T13:00:34Z","status":"RESOLVED","keywords":[],"component":"Performance: General","resolution":"INVALID"},{"keywords":[],"component":"Performance: General","resolution":"INCOMPLETE","last_change_time":"2024-07-01T12:23:26Z","op_sys":"Unspecified","summary":"Since the last update 121.0 Firefox uses insane amount of Ram 99% of my 32GB without any real reason and if it gets closed it buges out for 10 seconds spikes over the ram limit just to slowly close","creation_time":"2023-12-29T15:47:58Z","status":"RESOLVED","priority":"--","id":1872368,"severity":"--"},{"resolution":"INCOMPLETE","keywords":[],"component":"Performance: General","status":"RESOLVED","last_change_time":"2024-07-01T12:25:21Z","op_sys":"Unspecified","summary":"Firefox lags after latest update, high memory use (121.0 12-2023)","creation_time":"2023-12-30T00:34:35Z","priority":"--","id":1872414,"severity":"--"},{"severity":"--","id":1876708,"priority":"--","status":"RESOLVED","creation_time":"2024-01-26T11:03:08Z","last_change_time":"2025-03-21T01:04:43Z","op_sys":"Unspecified","summary":"firefox using 3.4gb of memory with a few tabs open","resolution":"INCOMPLETE","keywords":["perf:resource-use","perf:responsiveness"],"component":"Performance: Responsiveness"},{"component":"Performance: General","keywords":["perf:resource-use"],"resolution":"INCOMPLETE","creation_time":"2024-01-28T16:15:06Z","summary":"extremely high CPU usage even with one tab open on the splash screen","last_change_time":"2024-08-05T12:18:25Z","op_sys":"Unspecified","status":"RESOLVED","id":1877007,"priority":"--","severity":"--"},{"status":"RESOLVED","creation_time":"2024-02-07T20:00:44Z","last_change_time":"2024-08-05T15:01:21Z","op_sys":"Unspecified","severity":"--","summary":"3 youtube tabs are using 7GB of RAM","resolution":"INVALID","id":1879177,"keywords":["perf:resource-use"],"component":"Performance: General","priority":"--"},{"keywords":[],"component":"Performance: General","resolution":"INCOMPLETE","op_sys":"Unspecified","last_change_time":"2024-03-13T14:26:26Z","summary":"Firefox Freezes But Websites Don't","creation_time":"2024-02-12T02:38:12Z","status":"RESOLVED","priority":"--","id":1879788,"severity":"--"},{"keywords":["perf:resource-use"],"component":"Performance: General","resolution":"INCOMPLETE","last_change_time":"2024-09-02T12:20:43Z","op_sys":"Unspecified","summary":"firefox consuming 2 GB of RAM with 8 tabs open","creation_time":"2024-02-12T17:13:40Z","status":"RESOLVED","priority":"--","id":1879905,"severity":"--"},{"severity":"S3","summary":"tiktok.com - Live videos stop working after a few minutes, stuck loading","last_change_time":"2025-04-21T12:27:03Z","op_sys":"Windows 10","creation_time":"2024-02-14T13:36:20Z","status":"NEW","priority":"--","component":"Performance: General","keywords":[],"id":1880287,"resolution":""},{"summary":"Firefox consumes a lot of CPU and makes me Mac M2 hang for a good 15 seconds","last_change_time":"2024-05-21T13:37:47Z","op_sys":"Unspecified","creation_time":"2024-02-29T23:13:16Z","status":"UNCONFIRMED","component":"Performance: General","keywords":[],"resolution":"","severity":"--","priority":"--","id":1882916},{"resolution":"INCOMPLETE","component":"Performance: General","keywords":[],"status":"RESOLVED","creation_time":"2024-03-03T06:48:48Z","summary":"firefox using large amount of memory","last_change_time":"2024-09-02T12:20:29Z","op_sys":"Unspecified","id":1883246,"priority":"--","severity":"--"},{"priority":"--","id":1883475,"severity":"--","keywords":[],"component":"Performance: General","resolution":"","op_sys":"Unspecified","last_change_time":"2024-10-08T17:34:50Z","summary":"huge amount of memory storage (constantly) idk why pls help/.................................................................................................................................................","creation_time":"2024-03-04T19:20:05Z","status":"UNCONFIRMED"},{"status":"UNCONFIRMED","creation_time":"2024-03-04T22:03:15Z","summary":"Memory usage is too high 23GB and up to 60% CPU usage.","op_sys":"Unspecified","last_change_time":"2024-10-08T17:35:15Z","resolution":"","component":"Performance: General","keywords":[],"severity":"--","id":1883507,"priority":"--"},{"status":"UNCONFIRMED","creation_time":"2024-03-05T15:09:26Z","severity":"--","summary":"Memory Problem","op_sys":"Unspecified","last_change_time":"2024-10-08T17:34:40Z","resolution":"","id":1883669,"priority":"--","component":"Performance: General","keywords":[]},{"severity":"S3","id":1884296,"priority":"--","creation_time":"2024-03-08T03:56:55Z","summary":"Firefox is using lots of memory when only having several tabs open","op_sys":"Unspecified","last_change_time":"2024-10-08T17:34:42Z","status":"UNCONFIRMED","component":"Performance: General","keywords":["memory-footprint"],"resolution":""},{"id":1885796,"component":"Performance: General","priority":"--","keywords":[],"resolution":"INCOMPLETE","creation_time":"2024-03-17T18:24:37Z","summary":"Use to many Ram","severity":"--","op_sys":"Unspecified","last_change_time":"2025-03-31T12:27:19Z","status":"RESOLVED"},{"id":1891345,"keywords":[],"component":"Performance: General","priority":"--","resolution":"","creation_time":"2024-04-14T09:00:25Z","op_sys":"Unspecified","last_change_time":"2024-10-08T17:35:31Z","summary":"Enourmous RAM usage (60Gig)","severity":"--","status":"UNCONFIRMED"},{"creation_time":"2024-04-15T12:23:03Z","summary":"Update xsimd to new version 7eb009bca73e5cc51d05dcfcda25dfb74d6e0aaa from 2024-03-28 13:40:05","severity":"--","last_change_time":"2024-04-26T08:53:42Z","op_sys":"Unspecified","status":"RESOLVED","id":1891462,"component":"Performance: General","priority":"--","keywords":[],"resolution":"FIXED"},{"status":"RESOLVED","last_change_time":"2025-01-06T12:15:23Z","op_sys":"Unspecified","summary":"Uses a lot of ram, literally a lot even for less number of tabs opened","creation_time":"2024-04-23T23:06:49Z","resolution":"INCOMPLETE","keywords":[],"component":"Performance: General","severity":"--","priority":"--","id":1893080},{"creation_time":"2024-04-25T13:36:23Z","summary":"Memory Leak (Isolated Web Container)","severity":"--","op_sys":"Unspecified","last_change_time":"2024-12-02T12:31:51Z","status":"RESOLVED","id":1893459,"component":"Performance: General","priority":"--","keywords":[],"resolution":"INCOMPLETE"},{"severity":"--","summary":"firefox slows down, needs relaunch to restore throughput","last_change_time":"2025-01-06T17:00:36Z","op_sys":"Linux","creation_time":"2024-05-22T16:49:19Z","status":"RESOLVED","priority":"--","component":"Performance: General","keywords":[],"id":1898319,"resolution":"INACTIVE"},{"status":"RESOLVED","creation_time":"2024-07-19T09:07:38Z","severity":"--","summary":"www3.nhk.or.jp - The website is loaded after 1-2 seconds of blank page","last_change_time":"2025-03-31T09:59:19Z","op_sys":"Windows 11","resolution":"FIXED","id":1908857,"component":"Performance: General","priority":"P3","keywords":[]},{"id":1912758,"priority":"--","severity":"--","keywords":[],"component":"Performance: General","resolution":"INCOMPLETE","creation_time":"2024-08-12T13:10:00Z","op_sys":"Unspecified","last_change_time":"2025-05-05T12:25:43Z","summary":"Extreme CPU usage spike when typing into text fields","status":"RESOLVED"},{"resolution":"INCOMPLETE","id":1913407,"component":"Performance: General","priority":"--","keywords":[],"status":"RESOLVED","creation_time":"2024-08-16T04:45:39Z","summary":"the browser go crazy with cpu usage recently https://share.firefox.dev/3yIbAKI","severity":"--","last_change_time":"2025-05-05T12:26:59Z","op_sys":"Unspecified"},{"resolution":"INCOMPLETE","id":1914733,"keywords":[],"priority":"--","component":"Performance: General","status":"RESOLVED","creation_time":"2024-08-24T16:10:13Z","op_sys":"Unspecified","last_change_time":"2025-04-07T12:30:44Z","summary":"YouTube Freezing and consuming CPU usage","severity":"--"},{"resolution":"INCOMPLETE","id":1918065,"keywords":[],"component":"Performance: General","priority":"--","status":"RESOLVED","creation_time":"2024-09-11T10:37:14Z","last_change_time":"2025-04-07T12:30:19Z","op_sys":"Unspecified","summary":"High CPU/RAM utilisation using Firefox ESR without internet connectivity","severity":"--"},{"id":1924642,"keywords":[],"component":"Performance: General","priority":"--","resolution":"WORKSFORME","creation_time":"2024-10-15T08:05:21Z","last_change_time":"2025-05-07T07:41:07Z","op_sys":"Unspecified","summary":"Parent process and content processes sometimes consume lots of CPU (Tons of IPCOut — PContent::Msg_ScriptError)","severity":"--","status":"RESOLVED"},{"status":"RESOLVED","creation_time":"2024-10-30T14:33:29Z","op_sys":"Unspecified","last_change_time":"2024-12-26T14:34:32Z","summary":"Wiki page caused high CPU and RAM usage permanently","resolution":"WORKSFORME","keywords":[],"component":"Performance: General","severity":"--","id":1928090,"priority":"--"},{"resolution":"","keywords":["perf"],"component":"Performance: General","status":"UNCONFIRMED","last_change_time":"2024-12-26T14:21:04Z","op_sys":"Unspecified","summary":"since update 115.17.0esr (64 bits) my computer freezes and firefox takes 100% of the memory","creation_time":"2024-11-06T14:38:42Z","priority":"--","id":1929575,"severity":"--"},{"summary":"Firefox freezes on arch linux","severity":"--","last_change_time":"2025-01-13T15:26:58Z","op_sys":"Unspecified","creation_time":"2024-11-13T20:08:36Z","status":"RESOLVED","priority":"--","component":"Performance: General","keywords":[],"id":1931051,"resolution":"INACTIVE"},{"creation_time":"2024-11-14T16:01:57Z","severity":"--","summary":"Slow poor scrolling performance when using dual monitors.","last_change_time":"2024-12-26T14:36:27Z","op_sys":"Windows 10","status":"UNCONFIRMED","id":1931371,"component":"Performance: General","priority":"--","keywords":[],"resolution":""},{"status":"RESOLVED","summary":"nypost.com - Opening articles in multiple tabs crashes the browser (not responding)","op_sys":"Windows 10","last_change_time":"2025-04-23T12:49:42Z","creation_time":"2024-11-21T12:52:00Z","resolution":"FIXED","component":"Performance: General","keywords":["webcompat:site-report"],"severity":"--","priority":"--","id":1932607},{"status":"UNCONFIRMED","last_change_time":"2025-01-27T15:31:15Z","op_sys":"Unspecified","summary":"Memory leak in mac M1","severity":"--","creation_time":"2024-12-10T01:02:56Z","resolution":"","keywords":[],"component":"Performance: General","priority":"--","id":1936166},{"resolution":"INCOMPLETE","priority":"--","component":"Performance: General","keywords":[],"id":1939043,"status":"RESOLVED","summary":"Gmail freezes on 2nd Gmail account","severity":"--","op_sys":"Unspecified","last_change_time":"2025-05-07T08:54:47Z","creation_time":"2024-12-24T16:19:48Z"},{"status":"RESOLVED","creation_time":"2024-12-30T13:04:04Z","summary":"slowness","severity":"--","op_sys":"Unspecified","last_change_time":"2025-02-24T15:22:43Z","resolution":"INACTIVE","id":1939474,"component":"Performance: General","priority":"--","keywords":[]},{"resolution":"","component":"Performance: General","priority":"--","keywords":[],"id":1948186,"status":"NEW","severity":"--","summary":"paramountplus stream occasionally highly unresponsive","last_change_time":"2025-03-18T13:15:15Z","op_sys":"Unspecified","creation_time":"2025-02-14T06:55:56Z"},{"keywords":[],"component":"Performance: Responsiveness","resolution":"","last_change_time":"2025-04-25T13:16:59Z","op_sys":"Unspecified","summary":"Severe jank when scrolling and clicking on messages in large message list on Yahoo Mail","creation_time":"2025-03-22T11:55:14Z","status":"NEW","priority":"P3","id":1955749,"severity":"S3"},{"last_change_time":"2025-05-02T20:21:18Z","op_sys":"Unspecified","severity":"S3","summary":"High CPU usage after clicking buttons on at least one site","creation_time":"2025-03-27T20:24:11Z","status":"UNCONFIRMED","keywords":[],"component":"Performance: Responsiveness","priority":"--","id":1956931,"resolution":""},{"status":"UNCONFIRMED","creation_time":"2025-04-13T07:52:04Z","summary":"Dual monitor (laptop / Monitor) browsing very slow refresh in second monitor","severity":"--","last_change_time":"2025-05-09T12:11:00Z","op_sys":"Windows 11","resolution":"","id":1960195,"component":"Graphics","priority":"--","keywords":[]},{"resolution":"","priority":"--","component":"Performance: General","keywords":[],"id":1961523,"status":"UNCONFIRMED","severity":"--","summary":"Firefox constantly freezes","op_sys":"Unspecified","last_change_time":"2025-05-13T09:52:08Z","creation_time":"2025-04-20T11:59:18Z"},{"creation_time":"2025-05-01T21:23:59Z","summary":"Google search results in high CPU usage and spike in temps. Happens with most of the browsers but Firefox results in higher temps spikes and CPU usage","op_sys":"Windows 11","last_change_time":"2025-05-16T12:35:09Z","status":"UNCONFIRMED","component":"Performance: General","keywords":[],"resolution":"","severity":"--","id":1963933,"priority":"--"},{"creation_time":"2020-01-02T13:46:45Z","last_change_time":"2024-06-28T09:36:11Z","op_sys":"macOS","severity":"S3","summary":"Inefficient z-ordering of elements in the browser UI, causes large layers with current WebRender heuristics","status":"RESOLVED","id":1606631,"keywords":["perf:resource-use"],"priority":"P3","component":"Theme","resolution":"INCOMPLETE"},{"creation_time":"2022-08-19T06:50:58Z","op_sys":"Unspecified","last_change_time":"2024-05-02T16:48:19Z","summary":"Slow rendering and opening of certain PDF types","status":"RESOLVED","keywords":["regression"],"component":"PDF Viewer","resolution":"WORKSFORME","severity":"S3","id":1785979,"priority":"P3"},{"op_sys":"Unspecified","last_change_time":"2024-09-02T12:21:23Z","summary":"Firefox Browser Freezes when Opening Multiple Tabs","severity":"--","creation_time":"2024-03-01T03:39:28Z","status":"RESOLVED","keywords":[],"component":"Tabbed Browser","priority":"--","id":1882952,"resolution":"INCOMPLETE"}]}